iterlist.py
iterlist-0.4.dist-info/LICENSE.md
iterlist-0.4.dist-info/METADATA
iterlist-0.4.dist-info/WHEEL
iterlist-0.4.dist-info/top_level.txt
iterlist-0.4.dist-info/RECORD
