Metadata-Version: 2.1
Name: iterlist
Version: 0.4
Summary: Treat an iterator as a list
Home-page: https://github.west.isilon.com/masenf/iterlist
Author: Ryan Haining
Author-email: haining.cpp@gmail.com
Maintainer: Masen Furer
Maintainer-email: m_github@0x26.net
License: UNKNOWN
Platform: UNKNOWN
Classifier: Intended Audience :: Developers
Classifier: Development Status :: 3 - Alpha
Classifier: Operating System :: OS Independent
Classifier: License :: OSI Approved :: BSD License
Requires-Python: >=2.7,!=3.0.*,!=3.1.*,!=3.2.*,!=3.3.*,!=3.4.*,<4
